protobuf3_models/__init__.py
protobuf3_models/add.py
protobuf3_models/fields.py
protobuf3_models/models.py
setup_commands/__init__.py
setup_commands/clean.py
setup_commands/protoc.py
protobuf3_models-0.1.0.dist-info/LICENSE
protobuf3_models-0.1.0.dist-info/METADATA
protobuf3_models-0.1.0.dist-info/WHEEL
protobuf3_models-0.1.0.dist-info/top_level.txt
protobuf3_models-0.1.0.dist-info/RECORD
