Metadata-Version: 2.1
Name: protobuf3-models
Version: 0.1.0
Summary: Straightforward protobuf 3 handling through Python classes.
Home-page: https://github.com/mlga/protobuf3-models
Author: mlga
Author-email: github@mlga.io
License: MIT
Keywords: protobuf validation serialization
Platform: any
Requires-Python: >=3.7
Requires-Dist: protobuf (~=3.9)
Provides-Extra: develop
Requires-Dist: isort (~=5.6) ; extra == 'develop'
Requires-Dist: mypy (==0.790) ; extra == 'develop'
Requires-Dist: pre-commit (~=2.8) ; extra == 'develop'
Requires-Dist: pylint (~=2.3) ; extra == 'develop'
Requires-Dist: pytest (~=6.1) ; extra == 'develop'
Requires-Dist: pytest-cov (~=2.7) ; extra == 'develop'
Requires-Dist: pytest-html (~=2.1) ; extra == 'develop'
Requires-Dist: Sphinx (==3.0.1) ; extra == 'develop'
Requires-Dist: sphinx-rtd-theme (==0.4.3) ; extra == 'develop'
